setup.cfg
setup.py
vk_music/__init__.py
vk_music/__main__.py
vk_music/consts.py
vk_music/defaults.py
vk_music/exceptions.py
vk_music/storage.py
vk_music/utils.py
vk_music/vk_music.py
vk_music.egg-info/PKG-INFO
vk_music.egg-info/SOURCES.txt
vk_music.egg-info/dependency_links.txt
vk_music.egg-info/entry_points.txt
vk_music.egg-info/requires.txt
vk_music.egg-info/top_level.txt