Metadata-Version: 1.0
Name: vk-music
Version: 1.3.0
Summary: Synchronize music with vk.com
Home-page: https://github.com/sashasimkin/vk_music
Author: Alex Simkin
Author-email: sashasimkin@gmail.com
License: MIT
Keywords: vk.com,downloading,script
Platform: UNKNOWN
